aipt_v2/__init__.py
aipt_v2/__main__.py
aipt_v2/app.py
aipt_v2/cli.py
aipt_v2/config.py
aipt_v2/health.py
aipt_v2/interactive_shell.py
aipt_v2/local_tool_installer.py
aipt_v2/orchestrator.py
aipt_v2/prerequisites.py
aipt_v2/setup_wizard.py
aipt_v2/system_detector.py
aipt_v2/verify_install.py
aipt_v2/agents/__init__.py
aipt_v2/agents/base.py
aipt_v2/agents/coordinator.py
aipt_v2/agents/exploit_agent.py
aipt_v2/agents/ptt.py
aipt_v2/agents/state.py
aipt_v2/agents/AIPTxAgent/__init__.py
aipt_v2/agents/AIPTxAgent/aiptx_agent.py
aipt_v2/agents/AIPTxAgent/system_prompt.jinja
aipt_v2/agents/shared/__init__.py
aipt_v2/agents/shared/agent_pool.py
aipt_v2/agents/shared/finding_repository.py
aipt_v2/agents/shared/message_bus.py
aipt_v2/agents/specialized/__init__.py
aipt_v2/agents/specialized/base_specialized.py
aipt_v2/agents/specialized/business_logic_agent.py
aipt_v2/agents/specialized/dast_agent.py
aipt_v2/agents/specialized/recon_agent.py
aipt_v2/agents/specialized/sast_agent.py
aipt_v2/agents/specialized/websocket_agent.py
aipt_v2/browser/__init__.py
aipt_v2/browser/automation.py
aipt_v2/browser/crawler.py
aipt_v2/business_logic/__init__.py
aipt_v2/business_logic/analyzer.py
aipt_v2/business_logic/executor.py
aipt_v2/business_logic/test_generator.py
aipt_v2/business_logic/patterns/__init__.py
aipt_v2/business_logic/patterns/access_control.py
aipt_v2/business_logic/patterns/base.py
aipt_v2/business_logic/patterns/price_manipulation.py
aipt_v2/business_logic/patterns/race_conditions.py
aipt_v2/business_logic/patterns/rate_limiting.py
aipt_v2/business_logic/patterns/workflow.py
aipt_v2/compliance/__init__.py
aipt_v2/compliance/compliance_report.py
aipt_v2/compliance/framework_mapper.py
aipt_v2/compliance/nist_mapping.py
aipt_v2/compliance/owasp_mapping.py
aipt_v2/compliance/pci_mapping.py
aipt_v2/core/__init__.py
aipt_v2/core/agent.py
aipt_v2/core/event_loop_manager.py
aipt_v2/core/llm.py
aipt_v2/core/memory.py
aipt_v2/core/ptt.py
aipt_v2/database/__init__.py
aiptx-4.0.1.dist-info/licenses/LICENSE
aiptx-4.0.1.dist-info/METADATA
aiptx-4.0.1.dist-info/WHEEL
aiptx-4.0.1.dist-info/entry_points.txt
aiptx-4.0.1.dist-info/top_level.txt
aiptx-4.0.1.dist-info/RECORD
