Metadata-Version: 2.4
Name: aiptx
Version: 4.0.1
Summary: AI-assisted security testing framework with SAST, DAST, and business logic testing capabilities
Author-email: Satyam Rastogi <satyam@aiptx.io>
Maintainer-email: Satyam Rastogi <satyam@aiptx.io>
License: MIT License
Project-URL: Homepage, https://aiptx.io
Project-URL: Documentation, https://aiptx.io/docs
Project-URL: Repository, https://github.com/satyamrastogi/aiptx
Project-URL: Issues, https://github.com/satyamrastogi/aiptx/issues
Project-URL: Changelog, https://github.com/satyamrastogi/aiptx/blob/main/CHANGELOG.md
Project-URL: Community, https://aiptx.io/community
Keywords: security,penetration-testing,pentest,vulnerability-scanner,vulnerability-assessment,security-scanner,security-tools,security-automation,ai,llm,artificial-intelligence,machine-learning,gpt,chatgpt,cybersecurity,infosec,appsec,devsecops,vapt,dast,sast,bug-bounty,ethical-hacking,red-team,offensive-security,web-security,owasp,cve,exploit,sarif,cwe,nmap,nuclei,sqlmap,burp-suite,acunetix,nessus,zap,reconnaissance,recon,scanning,exploitation,graphql,websocket,spa,single-page-application,busin
Classifier: Development Status :: 4 - Beta
Classifier: Environment :: Console
Classifier: Environment :: Web Environment
Classifier: Intended Audience :: Developers
Classifier: Intended Audience :: Information Technology
Classifier: Intended Audience :: System Administrators
Classifier: Intended Audience :: Science/Research
Classifier: Topic :: Security
Classifier: Topic :: Security :: Cryptography
Classifier: Topic :: Software Development :: Testing
Classifier: Topic :: Software Development :: Testing :: Acceptance
Classifier: Topic :: Software Development :: Quality Assurance
Classifier: Topic :: Internet :: WWW/HTTP
Classifier: Topic :: Internet :: WWW/HTTP :: HTTP Servers
Classifier: Topic :: System :: Networking
Classifier: Topic :: System :: Systems Administration
Classifier: Topic :: System :: Monitoring
Classifier: Topic :: Utilities
Classifier: License :: OSI Approved :: MIT License
Classifier: Operating System :: OS Independent
Classifier: Operating System :: POSIX :: Linux
Classifier: Operating System :: MacOS
Classifier: Operating System :: Microsoft :: Windows
Classifier: Programming Language :: Python :: 3
Classifier: Programming Language :: Python :: 3.10
Classifier: Programming Language :: Python :: 3.11
Classifier: Programming Language :: Python :: 3.12
Classifier: Programming Language :: Python :: 3.13
Classifier: Programming Language :: Python :: Implementation :: CPython
Classifier: Typing :: Typed
Classifier: Framework :: FastAPI
Classifier: Natural Language :: English
Requires-Python: >=3.9
License-File: LICENSE
Requires-Dist: litellm>=1.50.0
Requires-Dist: jinja2>=3.1.0
Requires-Dist: tiktoken>=0.5.0
Requires-Dist: requests>=2.31.0
Requires-Dist: httpx>=0.25.0
Requires-Dist: aiohttp>=3.9.0
Requires-Dist: fastapi>=0.104.0
Requires-Dist: uvicorn[standard]>=0.24.0
Requires-Dist: pydantic>=2.5.0
Requires-Dist: pydantic-settings>=2.0.0
Requires-Dist: slowapi>=0.1.9
Requires-Dist: sqlalchemy>=2.0.0
Requires-Dist: alembic>=1.13.0
Requires-Dist: textual>=0.44.0
Requires-Dist: rich>=13.7.0
Requires-Dist: click>=8.1.0
Requires-Dist: typer>=0.9.0
Requires-Dist: pyyaml>=6.0
Requires-Dist: python-dotenv>=1.0.0
Requires-Dist: aiofiles>=23.0.0
Requires-Dist: structlog>=23.0.0
Requires-Dist: psutil>=5.9.0
Requires-Dist: websockets>=12.0
Provides-Extra: vps
Requires-Dist: asyncssh>=2.14.0; extra == "vps"
Provides-Extra: modern
Requires-Dist: playwright>=1.40.0; extra == "modern"
Requires-Dist: beautifulsoup4>=4.12.0; extra == "modern"
Requires-Dist: lxml>=5.0.0; extra == "modern"
Requires-Dist: aiohttp>=3.9.0; extra == "modern"
Requires-Dist: websockets>=12.0; extra == "modern"
Provides-Extra: sast
Requires-Dist: gitpython>=3.1.40; extra == "sast"
Requires-Dist: pyyaml>=6.0; extra == "sast"
Provides-Extra: full
Requires-Dist: sentence-transformers>=2.2.0; extra == "full"
Requires-Dist: numpy>=1.24.0; extra == "full"
Requires-Dist: torch>=2.0.0; extra == "full"
Requires-Dist: playwright>=1.40.0; extra == "full"
Requires-Dist: beautifulsoup4>=4.12.0; extra == "full"
Requires-Dist: lxml>=5.0.0; extra == "full"
Requires-Dist: gitpython>=3.1.40; extra == "full"
Requires-Dist: mitmproxy>=10.0.0; extra == "full"
Requires-Dist: docker>=7.0.0; extra == "full"
Requires-Dist: pexpect>=4.8.0; extra == "full"
Requires-Dist: paramiko>=3.4.0; extra == "full"
Requires-Dist: asyncssh>=2.14.0; extra == "full"
Requires-Dist: langchain-core>=0.1.0; extra == "full"
Requires-Dist: scikit-learn>=1.3.0; extra == "full"
Requires-Dist: scipy>=1.11.0; extra == "full"
Requires-Dist: pandas>=2.0.0; extra == "full"
Provides-Extra: cicd
Requires-Dist: jsonschema>=4.20.0; extra == "cicd"
Provides-Extra: dev
Requires-Dist: pytest>=7.4.0; extra == "dev"
Requires-Dist: pytest-asyncio>=0.21.0; extra == "dev"
Requires-Dist: pytest-cov>=4.1.0; extra == "dev"
Requires-Dist: pytest-mock>=3.12.0; extra == "dev"
Requires-Dist: black>=23.0.0; extra == "dev"
Requires-Dist: ruff>=0.1.0; extra == "dev"
Requires-Dist: mypy>=1.7.0; extra == "dev"
Requires-Dist: bandit>=1.7.0; extra == "dev"
Requires-Dist: pre-commit>=3.5.0; extra == "dev"
Requires-Dist: safety>=2.3.0; extra == "dev"
Provides-Extra: windows
Requires-Dist: pyreadline3>=3.4.0; extra == "windows"
Dynamic: license-file
